README.md
setup.py
yuki_queue/__init__.py
yuki_queue/batch.py
yuki_queue/context.py
yuki_queue/managers.py
yuki_queue.egg-info/PKG-INFO
yuki_queue.egg-info/SOURCES.txt
yuki_queue.egg-info/dependency_links.txt
yuki_queue.egg-info/top_level.txt