Metadata-Version: 2.1
Name: yuki-queue
Version: 0.0.1
Summary: A tiny but powerful distributed task queue for python.
Author: Stepfen Shawn
Author-email: m18824909883@163.com
Classifier: Programming Language :: Python :: 3
Classifier: License :: OSI Approved :: MIT License
Classifier: Operating System :: OS Independent
Requires-Python: >=3.6
